<?xml version="1.0" encoding="UTF-8"?>
<objects serializationModel="Studio.02.01.00">
	<object class="ParameterPreset" id="{460604aa-fc5a-429c-86ad-6d3536045938}">
		<property name="name">
			<value>Parameter 3</value>
		</property>
		<relationship name="folder">
			<destination>{b6de307e-db20-4644-84e1-8b1b9b4c1264}</destination>
		</relationship>
		<relationship name="parameter">
			<destination>{aac5d0b2-99da-44f0-bd7a-eb322fd008b2}</destination>
		</relationship>
	</object>
	<object class="GameParameter" id="{aac5d0b2-99da-44f0-bd7a-eb322fd008b2}">
		<property name="initialValue">
			<value>0</value>
		</property>
	</object>
</objects>
